pysal/__init__.py
pysal/base.py
pysal/explore/__init__.py
pysal/explore/esda/__init__.py
pysal/explore/giddy/__init__.py
pysal/explore/inequality/__init__.py
pysal/explore/momepy/__init__.py
pysal/explore/pointpats/__init__.py
pysal/explore/segregation/__init__.py
pysal/explore/spaghetti/__init__.py
pysal/lib/__init__.py
pysal/lib/common.py
pysal/lib/examples/__init__.py
pysal/model/__init__.py
pysal/model/access/__init__.py
pysal/model/gwlearn/__init__.py
pysal/model/mgwr/__init__.py
pysal/model/spglm/__init__.py
pysal/model/spint/__init__.py
pysal/model/spopt/__init__.py
pysal/model/spreg/__init__.py
pysal/model/tobler/__init__.py
pysal/tests/test_base.py
pysal/tests/test_common.py
pysal/tests/test_imports.py
pysal/viz/__init__.py
pysal/viz/mapclassify/__init__.py
pysal-26.1.dist-info/licenses/LICENSE.txt
pysal-26.1.dist-info/METADATA
pysal-26.1.dist-info/WHEEL
pysal-26.1.dist-info/top_level.txt
pysal-26.1.dist-info/RECORD
